gjaischool5313/test1.py
gjaischool5313/test2.py
gjaischool5313-0.0.0.2.dist-info/METADATA
gjaischool5313-0.0.0.2.dist-info/WHEEL
gjaischool5313-0.0.0.2.dist-info/top_level.txt
gjaischool5313-0.0.0.2.dist-info/RECORD
