Metadata-Version: 2.1
Name: gjaischool5313
Version: 0.0.0.2
Summary: 광주 ai school 5기 313번
Home-page: https://blog.naver.com/sun_day-s
Author: Dabin Choi
Author-email: gjaischool5.313@gmail.com
License: MIT
Requires-Python: >=3
